estnin.py
estnin-1.0.1.dist-info/LICENSE.txt
estnin-1.0.1.dist-info/METADATA
estnin-1.0.1.dist-info/WHEEL
estnin-1.0.1.dist-info/top_level.txt
estnin-1.0.1.dist-info/RECORD
