Metadata-Version: 2.1
Name: estnin
Version: 1.0.1
Summary: library for handling Estonian national identity numbers
Home-page: https://github.com/antirais/estnin
Author: Anti Räis
Author-email: antirais@gmail.com
License: MIT
Platform: UNKNOWN
Classifier: Development Status :: 5 - Production/Stable
Classifier: Intended Audience :: Developers
Classifier: License :: OSI Approved :: MIT License
Classifier: Programming Language :: Python :: 3
Classifier: Topic :: Software Development :: Libraries
Provides-Extra: test
Requires-Dist: coverage ; extra == 'test'
Requires-Dist: pytest ; extra == 'test'
Requires-Dist: pytest-cov ; extra == 'test'
